ConsoleQuestionPrompts/__init__.py
ConsoleQuestionPrompts/questions.py
ConsoleQuestionPrompts-2.0.0.dist-info/LICENSE
ConsoleQuestionPrompts-2.0.0.dist-info/METADATA
ConsoleQuestionPrompts-2.0.0.dist-info/WHEEL
ConsoleQuestionPrompts-2.0.0.dist-info/top_level.txt
ConsoleQuestionPrompts-2.0.0.dist-info/RECORD
