Metadata-Version: 2.1
Name: ConsoleQuestionPrompts
Version: 2.0.0
Summary: Facilitates asking questions to the user through the console.
Home-page: https://github.com/JEElsner/ConsoleQuestionPrompts
Author: Jonathan Elsner
Author-email: jelsnerbusiness@outlook.com
License: UNKNOWN
Platform: UNKNOWN
Classifier: Programming Language :: Python :: 3
Classifier: License :: OSI Approved :: MIT License
Classifier: Operating System :: OS Independent
Requires-Python: >=3.6
